pytijo_api_client/__init__.py
pytijo_api_client/command.py
pytijo_api_client/utils.py
pytijo_api_client-0.0.2.dist-info/METADATA
pytijo_api_client-0.0.2.dist-info/WHEEL
pytijo_api_client-0.0.2.dist-info/top_level.txt
pytijo_api_client-0.0.2.dist-info/zip-safe
pytijo_api_client-0.0.2.dist-info/RECORD
